monda/__init__.py
monda/WISP/__init__.py
monda/WISP/access.py
monda/WISP/plots.py
monda/hsp/__init__.py
monda/hsp/access.py
monda/minisecchi/__init__.py
monda/minisecchi/access.py
monda/sorad/__init__.py
monda/sorad/access.py
monda/sorad/plots.py
monda/sorad/qc.py
monda-0.3.0.dist-info/LICENSE
monda-0.3.0.dist-info/METADATA
monda-0.3.0.dist-info/WHEEL
monda-0.3.0.dist-info/top_level.txt
monda-0.3.0.dist-info/RECORD
