Metadata-Version: 2.1
Name: monda
Version: 0.3.0
Summary: A package for retrieval, quality control and analysis of Data from MONOCLE systems
Home-page: https://github.com/monocle-h2020/MONDA
Author: 
Author-email: 
Classifier: Programming Language :: Python :: 3
Classifier: License :: OSI Approved :: GNU General Public License v3 (GPLv3)
Classifier: Operating System :: OS Independent
Requires-Python: >=3.8
License-File: LICENSE
Requires-Dist: markdown
Requires-Dist: requests
Requires-Dist: cartopy>=0.20.2
Requires-Dist: matplotlib
Requires-Dist: numpy
Requires-Dist: scipy
Requires-Dist: pandas
Requires-Dist: datetime
Requires-Dist: argparse
